[
  {
    "code": 1810020001,
    "keccode": 1810020,
    "name": "KRESNOMULYO"
  },
  {
    "code": 1810020002,
    "keccode": 1810020,
    "name": "SUMBER AGUNG"
  },
  {
    "code": 1810020003,
    "keccode": 1810020,
    "name": "AMBARAWA"
  },
  {
    "code": 1810020004,
    "keccode": 1810020,
    "name": "AMBARAWA BARAT"
  },
  {
    "code": 1810020005,
    "keccode": 1810020,
    "name": "TANJUNG ANOM"
  },
  {
    "code": 1810020006,
    "keccode": 1810020,
    "name": "JATI AGUNG"
  },
  {
    "code": 1810020007,
    "keccode": 1810020,
    "name": "MARGODADI"
  },
  {
    "code": 1810020008,
    "keccode": 1810020,
    "name": "AMBARAWA TIMUR"
  }
]