[
  {
    "code": 3524120001,
    "keccode": 3524120,
    "name": "SIWALANREJO"
  },
  {
    "code": 3524120002,
    "keccode": 3524120,
    "name": "SUMBERAGUNG"
  },
  {
    "code": 3524120003,
    "keccode": 3524120,
    "name": "GEDANGAN"
  },
  {
    "code": 3524120004,
    "keccode": 3524120,
    "name": "BATURONO"
  },
  {
    "code": 3524120005,
    "keccode": 3524120,
    "name": "BANJAREJO"
  },
  {
    "code": 3524120006,
    "keccode": 3524120,
    "name": "SUMBERAJI"
  },
  {
    "code": 3524120007,
    "keccode": 3524120,
    "name": "KADUNGREMBUG"
  },
  {
    "code": 3524120008,
    "keccode": 3524120,
    "name": "MENONGO"
  },
  {
    "code": 3524120009,
    "keccode": 3524120,
    "name": "BALUNGTAWUN"
  },
  {
    "code": 3524120010,
    "keccode": 3524120,
    "name": "SUGIHREJO"
  },
  {
    "code": 3524120011,
    "keccode": 3524120,
    "name": "BANDUNGSARI"
  },
  {
    "code": 3524120012,
    "keccode": 3524120,
    "name": "PLUMPANG"
  },
  {
    "code": 3524120013,
    "keccode": 3524120,
    "name": "TLOGOREJO"
  },
  {
    "code": 3524120014,
    "keccode": 3524120,
    "name": "SURABAYAN"
  },
  {
    "code": 3524120015,
    "keccode": 3524120,
    "name": "SIDOGEMBUL"
  },
  {
    "code": 3524120016,
    "keccode": 3524120,
    "name": "SUKODADI"
  },
  {
    "code": 3524120017,
    "keccode": 3524120,
    "name": "KEBONSARI"
  },
  {
    "code": 3524120018,
    "keccode": 3524120,
    "name": "SUKOLILO"
  },
  {
    "code": 3524120019,
    "keccode": 3524120,
    "name": "PAJANGAN"
  },
  {
    "code": 3524120020,
    "keccode": 3524120,
    "name": "MADULEGI"
  }
]