[
  {
    "code": 1407060004,
    "keccode": 1407060,
    "name": "KEPENUHAN TENGAH"
  },
  {
    "code": 1407060005,
    "keccode": 1407060,
    "name": "KEPENUHAN BARAT"
  },
  {
    "code": 1407060006,
    "keccode": 1407060,
    "name": "KEPENUHAN RAYA"
  },
  {
    "code": 1407060007,
    "keccode": 1407060,
    "name": "KEPENUHAN BARU"
  },
  {
    "code": 1407060008,
    "keccode": 1407060,
    "name": "UPT SP III KOTO TENGAH/KEPENUHAN MAKMUR"
  },
  {
    "code": 1407060009,
    "keccode": 1407060,
    "name": "KEPENUHAN TIMUR"
  },
  {
    "code": 1407060010,
    "keccode": 1407060,
    "name": "KEPENUHAN HILIR"
  },
  {
    "code": 1407060011,
    "keccode": 1407060,
    "name": "UPT SP IV KOTO TENGAH/KEPENUHAN SEJATI"
  },
  {
    "code": 1407060012,
    "keccode": 1407060,
    "name": "KEPENUHAN SEI MANDIAN"
  },
  {
    "code": 1407060013,
    "keccode": 1407060,
    "name": "ULAK PATIAN"
  },
  {
    "code": 1407060016,
    "keccode": 1407060,
    "name": "RANTAU BINUANG SAKTI"
  },
  {
    "code": 1407060017,
    "keccode": 1407060,
    "name": "KEPENUHAN BARAT MULYA"
  },
  {
    "code": 1407060018,
    "keccode": 1407060,
    "name": "KEPENUHAN BARAT SUNGAI ROKAN JAYA"
  }
]