[
  {
    "code": 2103043001,
    "keccode": 2103043,
    "name": "SEDEDAP"
  },
  {
    "code": 2103043002,
    "keccode": 2103043,
    "name": "SABANG MAWANG"
  },
  {
    "code": 2103043004,
    "keccode": 2103043,
    "name": "TANJUNG BATANG"
  },
  {
    "code": 2103043005,
    "keccode": 2103043,
    "name": "SERANTAS"
  },
  {
    "code": 2103043006,
    "keccode": 2103043,
    "name": "SABANG MAWANG BARAT"
  },
  {
    "code": 2103043010,
    "keccode": 2103043,
    "name": "TELUK LABUH"
  }
]