[
  {
    "code": 7405070001,
    "keccode": 7405070,
    "name": "BAKUTARU"
  },
  {
    "code": 7405070002,
    "keccode": 7405070,
    "name": "PUDARIA JAYA"
  },
  {
    "code": 7405070003,
    "keccode": 7405070,
    "name": "SUMBER SARI"
  },
  {
    "code": 7405070004,
    "keccode": 7405070,
    "name": "ULUSENA"
  },
  {
    "code": 7405070022,
    "keccode": 7405070,
    "name": "WAWOSUNGGU"
  },
  {
    "code": 7405070023,
    "keccode": 7405070,
    "name": "PENAMBEA BARATA"
  },
  {
    "code": 7405070024,
    "keccode": 7405070,
    "name": "LAPUKO"
  },
  {
    "code": 7405070025,
    "keccode": 7405070,
    "name": "LAMBOO"
  },
  {
    "code": 7405070026,
    "keccode": 7405070,
    "name": "LANDIPO"
  },
  {
    "code": 7405070027,
    "keccode": 7405070,
    "name": "LAKOMEA"
  },
  {
    "code": 7405070028,
    "keccode": 7405070,
    "name": "MARGA CINTA"
  },
  {
    "code": 7405070029,
    "keccode": 7405070,
    "name": "MORAMO"
  },
  {
    "code": 7405070030,
    "keccode": 7405070,
    "name": "TAMBOSUPA"
  },
  {
    "code": 7405070031,
    "keccode": 7405070,
    "name": "AMOHOLA"
  },
  {
    "code": 7405070040,
    "keccode": 7405070,
    "name": "WAWONDENGI"
  },
  {
    "code": 7405070041,
    "keccode": 7405070,
    "name": "RANOOHA JAYA"
  },
  {
    "code": 7405070044,
    "keccode": 7405070,
    "name": "SELABANGGA"
  },
  {
    "code": 7405070045,
    "keccode": 7405070,
    "name": "WATU PORAMBAA"
  },
  {
    "code": 7405070046,
    "keccode": 7405070,
    "name": "WONUA JAYA"
  },
  {
    "code": 7405070047,
    "keccode": 7405070,
    "name": "BISIKORI"
  },
  {
    "code": 7405070048,
    "keccode": 7405070,
    "name": "UPT. PUUDURIA"
  }
]