[
  {
    "code": 7404071001,
    "keccode": 7404071,
    "name": "LAWULO"
  },
  {
    "code": 7404071002,
    "keccode": 7404071,
    "name": "SANI SANI"
  },
  {
    "code": 7404071003,
    "keccode": 7404071,
    "name": "KALOLOA"
  },
  {
    "code": 7404071004,
    "keccode": 7404071,
    "name": "KONAWEHA"
  },
  {
    "code": 7404071005,
    "keccode": 7404071,
    "name": "A W A"
  },
  {
    "code": 7404071006,
    "keccode": 7404071,
    "name": "LAMBOLEMO"
  },
  {
    "code": 7404071007,
    "keccode": 7404071,
    "name": "TAMBOLI"
  },
  {
    "code": 7404071008,
    "keccode": 7404071,
    "name": "TOSIBA"
  },
  {
    "code": 7404071009,
    "keccode": 7404071,
    "name": "AMOMUTU"
  },
  {
    "code": 7404071010,
    "keccode": 7404071,
    "name": "MALAHA"
  },
  {
    "code": 7404071011,
    "keccode": 7404071,
    "name": "LATUO"
  },
  {
    "code": 7404071012,
    "keccode": 7404071,
    "name": "WOWA TAMBOLI"
  },
  {
    "code": 7404071013,
    "keccode": 7404071,
    "name": "TONGANAPO"
  },
  {
    "code": 7404071014,
    "keccode": 7404071,
    "name": "ULU KONAWEHA"
  },
  {
    "code": 7404071015,
    "keccode": 7404071,
    "name": "PUUTAMBOLI"
  },
  {
    "code": 7404071016,
    "keccode": 7404071,
    "name": "PUU LAWULO"
  },
  {
    "code": 7404071017,
    "keccode": 7404071,
    "name": "LIKU"
  },
  {
    "code": 7404071018,
    "keccode": 7404071,
    "name": "MEURA"
  },
  {
    "code": 7404071019,
    "keccode": 7404071,
    "name": "ULAWENG"
  }
]