[
  {
    "code": 9101061001,
    "keccode": 9101061,
    "name": "DANA WERIA"
  },
  {
    "code": 9101061002,
    "keccode": 9101061,
    "name": "KAYU MERAH"
  },
  {
    "code": 9101061003,
    "keccode": 9101061,
    "name": "KATEMBA"
  },
  {
    "code": 9101061004,
    "keccode": 9101061,
    "name": "NEMEWIKARYA"
  },
  {
    "code": 9101061005,
    "keccode": 9101061,
    "name": "RADURIA"
  },
  {
    "code": 9101061006,
    "keccode": 9101061,
    "name": "BRONGKENDIK"
  },
  {
    "code": 9101061007,
    "keccode": 9101061,
    "name": "AIR BESAR"
  },
  {
    "code": 9101061008,
    "keccode": 9101061,
    "name": "KANANTARE"
  },
  {
    "code": 9101061009,
    "keccode": 9101061,
    "name": "MANDOPMA"
  },
  {
    "code": 9101061010,
    "keccode": 9101061,
    "name": "PASIR PUTIH"
  },
  {
    "code": 9101061011,
    "keccode": 9101061,
    "name": "PIRMA"
  },
  {
    "code": 9101061012,
    "keccode": 9101061,
    "name": "SAKARTEMIN"
  },
  {
    "code": 9101061013,
    "keccode": 9101061,
    "name": "UNI POKPOK"
  },
  {
    "code": 9101061014,
    "keccode": 9101061,
    "name": "HAMBRANGKENDIK"
  },
  {
    "code": 9101061015,
    "keccode": 9101061,
    "name": "KRABELANG"
  }
]