[
  {
    "code": 9412010020,
    "keccode": 9412010,
    "name": "KOKONAO"
  },
  {
    "code": 9412010021,
    "keccode": 9412010,
    "name": "MIGIWIA"
  },
  {
    "code": 9412010022,
    "keccode": 9412010,
    "name": "MIMIKA"
  },
  {
    "code": 9412010023,
    "keccode": 9412010,
    "name": "KIYURA"
  },
  {
    "code": 9412010024,
    "keccode": 9412010,
    "name": "APURI"
  },
  {
    "code": 9412010025,
    "keccode": 9412010,
    "name": "ATAPO"
  },
  {
    "code": 9412010026,
    "keccode": 9412010,
    "name": "APARUKA"
  }
]