[
  {
    "code": 3276011001,
    "keccode": 3276011,
    "name": "DUREN SERIBU"
  },
  {
    "code": 3276011002,
    "keccode": 3276011,
    "name": "DUREN MEKAR"
  },
  {
    "code": 3276011003,
    "keccode": 3276011,
    "name": "BOJONGSARI LAMA"
  },
  {
    "code": 3276011004,
    "keccode": 3276011,
    "name": "BOJONGSARI BARU"
  },
  {
    "code": 3276011006,
    "keccode": 3276011,
    "name": "PONDOK PETIR"
  },
  {
    "code": 3276011007,
    "keccode": 3276011,
    "name": "SERUA"
  }
]