[
  {
    "code": 1213080001,
    "keccode": 1213080,
    "name": "BESILAM BUKIT LEMBASA"
  },
  {
    "code": 1213080002,
    "keccode": 1213080,
    "name": "GERGAS"
  },
  {
    "code": 1213080003,
    "keccode": 1213080,
    "name": "BINGAI"
  },
  {
    "code": 1213080004,
    "keccode": 1213080,
    "name": "BUKIT MELINTANG"
  },
  {
    "code": 1213080005,
    "keccode": 1213080,
    "name": "KEBUN BALOK"
  },
  {
    "code": 1213080006,
    "keccode": 1213080,
    "name": "SUMBER MULYO"
  },
  {
    "code": 1213080007,
    "keccode": 1213080,
    "name": "GOHOR LAMA"
  },
  {
    "code": 1213080008,
    "keccode": 1213080,
    "name": "STABAT LAMA"
  },
  {
    "code": 1213080009,
    "keccode": 1213080,
    "name": "STABAT LAMA BARAT"
  },
  {
    "code": 1213080010,
    "keccode": 1213080,
    "name": "PERTUMBUKAN"
  },
  {
    "code": 1213080011,
    "keccode": 1213080,
    "name": "PAYA TUSAN"
  },
  {
    "code": 1213080012,
    "keccode": 1213080,
    "name": "MEKAR JAYA"
  },
  {
    "code": 1213080013,
    "keccode": 1213080,
    "name": "JENTERA STABAT"
  },
  {
    "code": 1213080014,
    "keccode": 1213080,
    "name": "STUNGKIT"
  }
]