[
  {
    "code": 1110090001,
    "keccode": 1110090,
    "name": "SUKARAME"
  },
  {
    "code": 1110090002,
    "keccode": 1110090,
    "name": "PANTON MESJID"
  },
  {
    "code": 1110090003,
    "keccode": 1110090,
    "name": "ALUE DUA"
  },
  {
    "code": 1110090004,
    "keccode": 1110090,
    "name": "BLANG PERLAK"
  },
  {
    "code": 1110090005,
    "keccode": 1110090,
    "name": "TANJONG MULIA"
  },
  {
    "code": 1110090006,
    "keccode": 1110090,
    "name": "MATANG KUMBANG"
  },
  {
    "code": 1110090007,
    "keccode": 1110090,
    "name": "MEUREUBO"
  },
  {
    "code": 1110090008,
    "keccode": 1110090,
    "name": "SEUNEUBOK BARO"
  },
  {
    "code": 1110090009,
    "keccode": 1110090,
    "name": "BLANG DALAM"
  },
  {
    "code": 1110090010,
    "keccode": 1110090,
    "name": "PANDAK"
  },
  {
    "code": 1110090011,
    "keccode": 1110090,
    "name": "BLANG MANE"
  },
  {
    "code": 1110090012,
    "keccode": 1110090,
    "name": "PANTE BREUH"
  },
  {
    "code": 1110090013,
    "keccode": 1110090,
    "name": "ULEE GLE"
  },
  {
    "code": 1110090014,
    "keccode": 1110090,
    "name": "MON ARA"
  },
  {
    "code": 1110090015,
    "keccode": 1110090,
    "name": "LAPEHAN MESJID"
  },
  {
    "code": 1110090016,
    "keccode": 1110090,
    "name": "BUKET SELAMAT"
  },
  {
    "code": 1110090017,
    "keccode": 1110090,
    "name": "BLANG KUTANG"
  },
  {
    "code": 1110090018,
    "keccode": 1110090,
    "name": "COT KRUET"
  },
  {
    "code": 1110090019,
    "keccode": 1110090,
    "name": "TRIENGGADENG"
  },
  {
    "code": 1110090020,
    "keccode": 1110090,
    "name": "LEUBU MESJID"
  },
  {
    "code": 1110090021,
    "keccode": 1110090,
    "name": "KUTA BARAT"
  },
  {
    "code": 1110090022,
    "keccode": 1110090,
    "name": "LEUBU COT"
  },
  {
    "code": 1110090023,
    "keccode": 1110090,
    "name": "PAYA DUA"
  },
  {
    "code": 1110090024,
    "keccode": 1110090,
    "name": "LEUBU ME"
  },
  {
    "code": 1110090025,
    "keccode": 1110090,
    "name": "BATEE DABAI"
  },
  {
    "code": 1110090026,
    "keccode": 1110090,
    "name": "PULO TEUNGOH"
  },
  {
    "code": 1110090027,
    "keccode": 1110090,
    "name": "ARA LIPEH"
  }
]