[
  {
    "code": 1904021001,
    "keccode": 1904021,
    "name": "BELILIK"
  },
  {
    "code": 1904021002,
    "keccode": 1904021,
    "name": "NAMANG"
  },
  {
    "code": 1904021004,
    "keccode": 1904021,
    "name": "CAMBAI"
  },
  {
    "code": 1904021005,
    "keccode": 1904021,
    "name": "KAYU BESI"
  },
  {
    "code": 1904021006,
    "keccode": 1904021,
    "name": "BUKIT KIJANG"
  },
  {
    "code": 1904021007,
    "keccode": 1904021,
    "name": "BASKARA BAKTI"
  },
  {
    "code": 1904021008,
    "keccode": 1904021,
    "name": "CAMBAI SELATAN"
  }
]