[
  {
    "code": 7502082001,
    "keccode": 7502082,
    "name": "TUALANGO"
  },
  {
    "code": 7502082002,
    "keccode": 7502082,
    "name": "DULOMO"
  },
  {
    "code": 7502082003,
    "keccode": 7502082,
    "name": "TILOTE"
  },
  {
    "code": 7502082004,
    "keccode": 7502082,
    "name": "TABUMELA"
  },
  {
    "code": 7502082005,
    "keccode": 7502082,
    "name": "ILOTIDEA"
  },
  {
    "code": 7502082006,
    "keccode": 7502082,
    "name": "LAUWONU"
  },
  {
    "code": 7502082007,
    "keccode": 7502082,
    "name": "TENGGELA"
  },
  {
    "code": 7502082008,
    "keccode": 7502082,
    "name": "TINELO"
  }
]