[
  {
    "code": 1809021001,
    "keccode": 1809021,
    "name": "BATU MENYAN"
  },
  {
    "code": 1809021002,
    "keccode": 1809021,
    "name": "GEBANG"
  },
  {
    "code": 1809021003,
    "keccode": 1809021,
    "name": "SIDODADI"
  },
  {
    "code": 1809021004,
    "keccode": 1809021,
    "name": "HANURA"
  },
  {
    "code": 1809021005,
    "keccode": 1809021,
    "name": "CILIMUS"
  },
  {
    "code": 1809021006,
    "keccode": 1809021,
    "name": "HURUN"
  },
  {
    "code": 1809021007,
    "keccode": 1809021,
    "name": "SUKAJAYA LEMPASING"
  },
  {
    "code": 1809021008,
    "keccode": 1809021,
    "name": "MUNCA"
  },
  {
    "code": 1809021009,
    "keccode": 1809021,
    "name": "TANJUNG AGUNG"
  },
  {
    "code": 1809021010,
    "keccode": 1809021,
    "name": "TALANG MULYO"
  }
]