[
  {
    "code": 1611040001,
    "keccode": 1611040,
    "name": "PENANTIAN"
  },
  {
    "code": 1611040002,
    "keccode": 1611040,
    "name": "TALANG PADANG"
  },
  {
    "code": 1611040003,
    "keccode": 1611040,
    "name": "TANJUNG BERINGIN"
  },
  {
    "code": 1611040004,
    "keccode": 1611040,
    "name": "LAWANG AGUNG"
  },
  {
    "code": 1611040005,
    "keccode": 1611040,
    "name": "PAGAR JATI"
  },
  {
    "code": 1611040006,
    "keccode": 1611040,
    "name": "BANDAR AGUNG"
  },
  {
    "code": 1611040007,
    "keccode": 1611040,
    "name": "KEBAN JATI"
  },
  {
    "code": 1611040008,
    "keccode": 1611040,
    "name": "NANJUNGAN"
  },
  {
    "code": 1611040009,
    "keccode": 1611040,
    "name": "TALANG RANDAI"
  },
  {
    "code": 1611040010,
    "keccode": 1611040,
    "name": "AIR MAYAN"
  },
  {
    "code": 1611040011,
    "keccode": 1611040,
    "name": "PADANG GELAI"
  },
  {
    "code": 1611040012,
    "keccode": 1611040,
    "name": "MUARA RUNGGA"
  },
  {
    "code": 1611040013,
    "keccode": 1611040,
    "name": "PADANG BINDU"
  },
  {
    "code": 1611040014,
    "keccode": 1611040,
    "name": "MUARA SINDANG"
  },
  {
    "code": 1611040015,
    "keccode": 1611040,
    "name": "MUARA AMAN"
  }
]