[
  {
    "code": 1214030006,
    "keccode": 1214030,
    "name": "HILIGEHO"
  },
  {
    "code": 1214030007,
    "keccode": 1214030,
    "name": "HILITOBARA"
  },
  {
    "code": 1214030008,
    "keccode": 1214030,
    "name": "PASAR TELUK DALAM"
  },
  {
    "code": 1214030009,
    "keccode": 1214030,
    "name": "BAWONIFAOSO"
  },
  {
    "code": 1214030010,
    "keccode": 1214030,
    "name": "BAWOZAUA"
  },
  {
    "code": 1214030011,
    "keccode": 1214030,
    "name": "HILIGANOWO"
  },
  {
    "code": 1214030022,
    "keccode": 1214030,
    "name": "BAWODOBARA"
  },
  {
    "code": 1214030023,
    "keccode": 1214030,
    "name": "BAWOLOWALANI"
  },
  {
    "code": 1214030024,
    "keccode": 1214030,
    "name": "HILISONDREKHA"
  },
  {
    "code": 1214030025,
    "keccode": 1214030,
    "name": "HILISAOOTONIHA"
  },
  {
    "code": 1214030040,
    "keccode": 1214030,
    "name": "HILIANAA"
  },
  {
    "code": 1214030041,
    "keccode": 1214030,
    "name": "HILIGANOWO SALOO"
  },
  {
    "code": 1214030042,
    "keccode": 1214030,
    "name": "HILIGANOWOSA'UA"
  },
  {
    "code": 1214030043,
    "keccode": 1214030,
    "name": "HILILAZA"
  },
  {
    "code": 1214030044,
    "keccode": 1214030,
    "name": "NANOWA"
  }
]