[
  {
    "code": 1108110014,
    "keccode": 1108110,
    "name": "DEUNONG"
  },
  {
    "code": 1108110015,
    "keccode": 1108110,
    "name": "LEU GEU"
  },
  {
    "code": 1108110017,
    "keccode": 1108110,
    "name": "LAMSITEH"
  },
  {
    "code": 1108110018,
    "keccode": 1108110,
    "name": "LAMPEUNEUEN"
  },
  {
    "code": 1108110019,
    "keccode": 1108110,
    "name": "ULEE TUY"
  },
  {
    "code": 1108110020,
    "keccode": 1108110,
    "name": "PUNIE"
  },
  {
    "code": 1108110021,
    "keccode": 1108110,
    "name": "LEU UE"
  },
  {
    "code": 1108110022,
    "keccode": 1108110,
    "name": "GEUNDRING"
  },
  {
    "code": 1108110023,
    "keccode": 1108110,
    "name": "PASHEU BEUTONG"
  },
  {
    "code": 1108110024,
    "keccode": 1108110,
    "name": "LAMPASI ENGKING"
  },
  {
    "code": 1108110025,
    "keccode": 1108110,
    "name": "JEUMPET AJUN"
  },
  {
    "code": 1108110026,
    "keccode": 1108110,
    "name": "GAROT"
  },
  {
    "code": 1108110027,
    "keccode": 1108110,
    "name": "GUE GAJAH"
  },
  {
    "code": 1108110028,
    "keccode": 1108110,
    "name": "ULEE LUENG"
  },
  {
    "code": 1108110029,
    "keccode": 1108110,
    "name": "LAM BHEU"
  },
  {
    "code": 1108110030,
    "keccode": 1108110,
    "name": "KANDANG"
  },
  {
    "code": 1108110031,
    "keccode": 1108110,
    "name": "DAROY KAMEU"
  },
  {
    "code": 1108110032,
    "keccode": 1108110,
    "name": "TINGKEUM"
  },
  {
    "code": 1108110033,
    "keccode": 1108110,
    "name": "LAMTHEUN"
  },
  {
    "code": 1108110034,
    "keccode": 1108110,
    "name": "LAMSIDAYA"
  },
  {
    "code": 1108110035,
    "keccode": 1108110,
    "name": "KUTA KARANG"
  },
  {
    "code": 1108110036,
    "keccode": 1108110,
    "name": "LAMKAWEE"
  },
  {
    "code": 1108110037,
    "keccode": 1108110,
    "name": "LHEU BLANG"
  },
  {
    "code": 1108110038,
    "keccode": 1108110,
    "name": "LAGANG"
  },
  {
    "code": 1108110039,
    "keccode": 1108110,
    "name": "LAMBLANG MANYANG"
  },
  {
    "code": 1108110040,
    "keccode": 1108110,
    "name": "LAMBLANG TRIENG"
  },
  {
    "code": 1108110041,
    "keccode": 1108110,
    "name": "PAYAROH"
  },
  {
    "code": 1108110042,
    "keccode": 1108110,
    "name": "LAMPEUNEURUT UJONG BLANG"
  },
  {
    "code": 1108110043,
    "keccode": 1108110,
    "name": "LAMPEUNEURUT GAMPONG"
  },
  {
    "code": 1108110044,
    "keccode": 1108110,
    "name": "LAMCOT"
  },
  {
    "code": 1108110045,
    "keccode": 1108110,
    "name": "LAMREUNG"
  },
  {
    "code": 1108110046,
    "keccode": 1108110,
    "name": "BAYU"
  }
]