[
  {
    "code": 9105144001,
    "keccode": 9105144,
    "name": "ACEMO"
  },
  {
    "code": 9105144002,
    "keccode": 9105144,
    "name": "WARSUAMI"
  },
  {
    "code": 9105144004,
    "keccode": 9105144,
    "name": "MUPI"
  },
  {
    "code": 9105144007,
    "keccode": 9105144,
    "name": "ANGRISI"
  },
  {
    "code": 9105144009,
    "keccode": 9105144,
    "name": "MISAPMEYSI"
  },
  {
    "code": 9105144012,
    "keccode": 9105144,
    "name": "MARUNI"
  },
  {
    "code": 9105144013,
    "keccode": 9105144,
    "name": "WAMESA"
  },
  {
    "code": 9105144014,
    "keccode": 9105144,
    "name": "ANDAY"
  },
  {
    "code": 9105144015,
    "keccode": 9105144,
    "name": "WARURI / WELURI"
  },
  {
    "code": 9105144016,
    "keccode": 9105144,
    "name": "WASAY"
  },
  {
    "code": 9105144017,
    "keccode": 9105144,
    "name": "WARMUMI"
  },
  {
    "code": 9105144018,
    "keccode": 9105144,
    "name": "DIHARA"
  },
  {
    "code": 9105144019,
    "keccode": 9105144,
    "name": "KATEBU"
  },
  {
    "code": 9105144020,
    "keccode": 9105144,
    "name": "MASIEPI"
  },
  {
    "code": 9105144021,
    "keccode": 9105144,
    "name": "SOWI"
  },
  {
    "code": 9105144022,
    "keccode": 9105144,
    "name": "DOPUT"
  },
  {
    "code": 9105144023,
    "keccode": 9105144,
    "name": "WARKOMI"
  },
  {
    "code": 9105144024,
    "keccode": 9105144,
    "name": "NGINYBOU / NGUNIBOUW"
  }
]