[
  {
    "code": 1672010001,
    "keccode": 1672010,
    "name": "RAMBANG SENULING"
  },
  {
    "code": 1672010002,
    "keccode": 1672010,
    "name": "TANJUNG RAMBANG"
  },
  {
    "code": 1672010003,
    "keccode": 1672010,
    "name": "KARANG BINDU"
  },
  {
    "code": 1672010005,
    "keccode": 1672010,
    "name": "KARYA MULYA"
  },
  {
    "code": 1672010006,
    "keccode": 1672010,
    "name": "SINAR RAMBANG"
  },
  {
    "code": 1672010007,
    "keccode": 1672010,
    "name": "JUNGAI"
  },
  {
    "code": 1672010008,
    "keccode": 1672010,
    "name": "TALANG BATU"
  },
  {
    "code": 1672010009,
    "keccode": 1672010,
    "name": "KARANGAN"
  },
  {
    "code": 1672010010,
    "keccode": 1672010,
    "name": "KEMANG TANDUK"
  }
]