[
  {
    "code": 7108060001,
    "keccode": 7108060,
    "name": "TAPILE"
  },
  {
    "code": 7108060002,
    "keccode": 7108060,
    "name": "BUHIAS"
  },
  {
    "code": 7108060003,
    "keccode": 7108060,
    "name": "BALIRANGEN"
  },
  {
    "code": 7108060004,
    "keccode": 7108060,
    "name": "BIAU"
  },
  {
    "code": 7108060005,
    "keccode": 7108060,
    "name": "BANDIL"
  },
  {
    "code": 7108060006,
    "keccode": 7108060,
    "name": "SAWANG"
  },
  {
    "code": 7108060007,
    "keccode": 7108060,
    "name": "PANGIROLONG"
  },
  {
    "code": 7108060008,
    "keccode": 7108060,
    "name": "MALA"
  },
  {
    "code": 7108060009,
    "keccode": 7108060,
    "name": "BINALU"
  },
  {
    "code": 7108060010,
    "keccode": 7108060,
    "name": "KALIHIANG"
  },
  {
    "code": 7108060011,
    "keccode": 7108060,
    "name": "LAHOPANG"
  },
  {
    "code": 7108060012,
    "keccode": 7108060,
    "name": "PAHEPA"
  },
  {
    "code": 7108060013,
    "keccode": 7108060,
    "name": "MATOLE"
  },
  {
    "code": 7108060014,
    "keccode": 7108060,
    "name": "BIAU SEHA"
  }
]