[
  {
    "code": 1802010003,
    "keccode": 1802010,
    "name": "KARANG ANYAR"
  },
  {
    "code": 1802010008,
    "keccode": 1802010,
    "name": "KALIREJO"
  },
  {
    "code": 1802010009,
    "keccode": 1802010,
    "name": "DADIREJO"
  },
  {
    "code": 1802010010,
    "keccode": 1802010,
    "name": "BANYU URIP"
  },
  {
    "code": 1802010011,
    "keccode": 1802010,
    "name": "WONOSOBO"
  },
  {
    "code": 1802010012,
    "keccode": 1802010,
    "name": "SOPONYONO"
  },
  {
    "code": 1802010013,
    "keccode": 1802010,
    "name": "BANDAR KEJADIAN"
  },
  {
    "code": 1802010014,
    "keccode": 1802010,
    "name": "WAY PANAS"
  },
  {
    "code": 1802010015,
    "keccode": 1802010,
    "name": "SINAR SAUDARA"
  },
  {
    "code": 1802010016,
    "keccode": 1802010,
    "name": "SRIDADI"
  },
  {
    "code": 1802010017,
    "keccode": 1802010,
    "name": "LAKARAN"
  },
  {
    "code": 1802010018,
    "keccode": 1802010,
    "name": "PADANG RATU"
  },
  {
    "code": 1802010019,
    "keccode": 1802010,
    "name": "PARDA SUKA"
  },
  {
    "code": 1802010020,
    "keccode": 1802010,
    "name": "TANJUNG KURUNG"
  },
  {
    "code": 1802010021,
    "keccode": 1802010,
    "name": "PADANG MANIS"
  },
  {
    "code": 1802010022,
    "keccode": 1802010,
    "name": "KEJADIAN"
  },
  {
    "code": 1802010023,
    "keccode": 1802010,
    "name": "DADISARI"
  },
  {
    "code": 1802010024,
    "keccode": 1802010,
    "name": "KALISARI"
  },
  {
    "code": 1802010029,
    "keccode": 1802010,
    "name": "BANJAR NEGORO"
  },
  {
    "code": 1802010030,
    "keccode": 1802010,
    "name": "PEKON BALAK"
  },
  {
    "code": 1802010031,
    "keccode": 1802010,
    "name": "KUNYAYAN"
  },
  {
    "code": 1802010032,
    "keccode": 1802010,
    "name": "BANJARSARI"
  },
  {
    "code": 1802010037,
    "keccode": 1802010,
    "name": "NEGERI NGARIP"
  },
  {
    "code": 1802010038,
    "keccode": 1802010,
    "name": "SAMPANG TURUS"
  },
  {
    "code": 1802010039,
    "keccode": 1802010,
    "name": "WAY LIWOK"
  },
  {
    "code": 1802010040,
    "keccode": 1802010,
    "name": "SUMUR TUJUH"
  },
  {
    "code": 1802010041,
    "keccode": 1802010,
    "name": "DADI MULYO"
  },
  {
    "code": 1802010042,
    "keccode": 1802010,
    "name": "SRI MELATI"
  }
]