[
  {
    "code": 7402062001,
    "keccode": 7402062,
    "name": "LABAHA"
  },
  {
    "code": 7402062002,
    "keccode": 7402062,
    "name": "WATOPUTE"
  },
  {
    "code": 7402062003,
    "keccode": 7402062,
    "name": "BANGKALI"
  },
  {
    "code": 7402062004,
    "keccode": 7402062,
    "name": "BHANGKALI BARAT"
  },
  {
    "code": 7402062005,
    "keccode": 7402062,
    "name": "DANA"
  },
  {
    "code": 7402062006,
    "keccode": 7402062,
    "name": "LAKAPODO"
  },
  {
    "code": 7402062007,
    "keccode": 7402062,
    "name": "WAKADIA"
  },
  {
    "code": 7402062008,
    "keccode": 7402062,
    "name": "MATARAWA"
  },
  {
    "code": 7402062009,
    "keccode": 7402062,
    "name": "WALI"
  },
  {
    "code": 7402062010,
    "keccode": 7402062,
    "name": "DANA TIMUR"
  },
  {
    "code": 7402062011,
    "keccode": 7402062,
    "name": "WAKADIA BARAT"
  }
]