[
  {
    "code": 8204042001,
    "keccode": 8204042,
    "name": "TAWA BACAN TIMUR"
  },
  {
    "code": 8204042002,
    "keccode": 8204042,
    "name": "SONGA"
  },
  {
    "code": 8204042003,
    "keccode": 8204042,
    "name": "BIBINOI"
  },
  {
    "code": 8204042004,
    "keccode": 8204042,
    "name": "TABAPOMA"
  },
  {
    "code": 8204042005,
    "keccode": 8204042,
    "name": "TUTUPA"
  },
  {
    "code": 8204042006,
    "keccode": 8204042,
    "name": "TOMARA"
  },
  {
    "code": 8204042007,
    "keccode": 8204042,
    "name": "WAYATIM"
  }
]