[
  {
    "code": 6205061001,
    "keccode": 6205061,
    "name": "NIHAN HILIR"
  },
  {
    "code": 6205061002,
    "keccode": 6205061,
    "name": "NIHAN HULU"
  },
  {
    "code": 6205061003,
    "keccode": 6205061,
    "name": "LUWE HILIR"
  },
  {
    "code": 6205061005,
    "keccode": 6205061,
    "name": "JANGKANG BARU"
  },
  {
    "code": 6205061006,
    "keccode": 6205061,
    "name": "JANGKANG LAMA"
  },
  {
    "code": 6205061007,
    "keccode": 6205061,
    "name": "PAPAR PUJUNG"
  },
  {
    "code": 6205061008,
    "keccode": 6205061,
    "name": "TELUK MALEWAI"
  },
  {
    "code": 6205061009,
    "keccode": 6205061,
    "name": "BENAO HILIR"
  },
  {
    "code": 6205061010,
    "keccode": 6205061,
    "name": "BENAO HULU"
  },
  {
    "code": 6205061011,
    "keccode": 6205061,
    "name": "KARAMUAN"
  }
]