[
  {
    "code": 8206033001,
    "keccode": 8206033,
    "name": "IGA"
  },
  {
    "code": 8206033002,
    "keccode": 8206033,
    "name": "LABI LABI"
  },
  {
    "code": 8206033003,
    "keccode": 8206033,
    "name": "TATAM"
  },
  {
    "code": 8206033004,
    "keccode": 8206033,
    "name": "MARIMOI"
  },
  {
    "code": 8206033005,
    "keccode": 8206033,
    "name": "BOLOLO"
  },
  {
    "code": 8206033006,
    "keccode": 8206033,
    "name": "HILAITETOR"
  },
  {
    "code": 8206033007,
    "keccode": 8206033,
    "name": "DOWONGI JAYA"
  },
  {
    "code": 8206033008,
    "keccode": 8206033,
    "name": "MAJIKO TONGONE"
  }
]