[
  {
    "code": 1601091001,
    "keccode": 1601091,
    "name": "MERBAU"
  },
  {
    "code": 1601091002,
    "keccode": 1601091,
    "name": "GUNUNG MERAKSA"
  },
  {
    "code": 1601091003,
    "keccode": 1601091,
    "name": "KURUP"
  },
  {
    "code": 1601091004,
    "keccode": 1601091,
    "name": "BANU AYU"
  },
  {
    "code": 1601091006,
    "keccode": 1601091,
    "name": "TANJUNG DALAM"
  },
  {
    "code": 1601091007,
    "keccode": 1601091,
    "name": "LUBUK BATANG BARU"
  },
  {
    "code": 1601091008,
    "keccode": 1601091,
    "name": "LUBUK BATANG LAMA"
  },
  {
    "code": 1601091010,
    "keccode": 1601091,
    "name": "BELATUNG"
  },
  {
    "code": 1601091011,
    "keccode": 1601091,
    "name": "KARTA MULIA"
  },
  {
    "code": 1601091012,
    "keccode": 1601091,
    "name": "MARKISA"
  },
  {
    "code": 1601091013,
    "keccode": 1601091,
    "name": "LUNGGAIAN BARU/AIR WAL"
  },
  {
    "code": 1601091014,
    "keccode": 1601091,
    "name": "LUNGGAIAN"
  },
  {
    "code": 1601091015,
    "keccode": 1601091,
    "name": "TANJUNG MANGGUS"
  },
  {
    "code": 1601091016,
    "keccode": 1601091,
    "name": "BANDAR AGUNG"
  },
  {
    "code": 1601091017,
    "keccode": 1601091,
    "name": "SUMBER BAHAGIA"
  }
]