[
  {
    "code": 1114061001,
    "keccode": 1114061,
    "name": "SUKAJADI"
  },
  {
    "code": 1114061002,
    "keccode": 1114061,
    "name": "SUKA DAMAI"
  },
  {
    "code": 1114061003,
    "keccode": 1114061,
    "name": "PAYA RAHAT"
  },
  {
    "code": 1114061004,
    "keccode": 1114061,
    "name": "SUKA MULIA/UPAH HULU"
  },
  {
    "code": 1114061005,
    "keccode": 1114061,
    "name": "MATANG SEUPING"
  },
  {
    "code": 1114061006,
    "keccode": 1114061,
    "name": "GAMPONG BESAR"
  },
  {
    "code": 1114061007,
    "keccode": 1114061,
    "name": "TELAGA MEUKU II"
  },
  {
    "code": 1114061008,
    "keccode": 1114061,
    "name": "TELAGA MEUKU I"
  },
  {
    "code": 1114061009,
    "keccode": 1114061,
    "name": "TANJUNG KERAMAT"
  },
  {
    "code": 1114061010,
    "keccode": 1114061,
    "name": "ALUR NUNANG"
  }
]