[
  {
    "code": 3527020007,
    "keccode": 3527020,
    "name": "DULANG"
  },
  {
    "code": 3527020008,
    "keccode": 3527020,
    "name": "PATARONGAN"
  },
  {
    "code": 3527020009,
    "keccode": 3527020,
    "name": "PANGONGSEAN"
  },
  {
    "code": 3527020010,
    "keccode": 3527020,
    "name": "KRAMPON"
  },
  {
    "code": 3527020011,
    "keccode": 3527020,
    "name": "BRINGIN NONGGAL"
  },
  {
    "code": 3527020012,
    "keccode": 3527020,
    "name": "TORJUN"
  },
  {
    "code": 3527020013,
    "keccode": 3527020,
    "name": "PATAPAN"
  },
  {
    "code": 3527020014,
    "keccode": 3527020,
    "name": "JERUK POROT"
  },
  {
    "code": 3527020015,
    "keccode": 3527020,
    "name": "KODAK"
  },
  {
    "code": 3527020016,
    "keccode": 3527020,
    "name": "KANJAR"
  },
  {
    "code": 3527020017,
    "keccode": 3527020,
    "name": "KARA"
  },
  {
    "code": 3527020018,
    "keccode": 3527020,
    "name": "TANA MERA"
  }
]