[
  {
    "code": 3209081001,
    "keccode": 3209081,
    "name": "ASTANAMUKTI"
  },
  {
    "code": 3209081002,
    "keccode": 3209081,
    "name": "PENGARENGAN"
  },
  {
    "code": 3209081003,
    "keccode": 3209081,
    "name": "JAPURA LOR"
  },
  {
    "code": 3209081004,
    "keccode": 3209081,
    "name": "BERINGIN"
  },
  {
    "code": 3209081005,
    "keccode": 3209081,
    "name": "RAWAURIP"
  },
  {
    "code": 3209081006,
    "keccode": 3209081,
    "name": "BENDUNGAN"
  },
  {
    "code": 3209081007,
    "keccode": 3209081,
    "name": "PANGENAN"
  },
  {
    "code": 3209081008,
    "keccode": 3209081,
    "name": "GETRAKMOYAN"
  }
]