[
  {
    "code": 7311150001,
    "keccode": 7311150,
    "name": "SAMAENRE"
  },
  {
    "code": 7311150002,
    "keccode": 7311150,
    "name": "WALIMPONG"
  },
  {
    "code": 7311150004,
    "keccode": 7311150,
    "name": "SELLI"
  },
  {
    "code": 7311150005,
    "keccode": 7311150,
    "name": "BULU ALLAPPORENGE"
  },
  {
    "code": 7311150006,
    "keccode": 7311150,
    "name": "BENGO"
  },
  {
    "code": 7311150007,
    "keccode": 7311150,
    "name": "MATTARO PULI"
  },
  {
    "code": 7311150008,
    "keccode": 7311150,
    "name": "MATTIRO WALIE"
  },
  {
    "code": 7311150009,
    "keccode": 7311150,
    "name": "LILIRIAWANG"
  }
]