[
  {
    "code": 8109050001,
    "keccode": 8109050,
    "name": "SIWAR"
  },
  {
    "code": 8109050002,
    "keccode": 8109050,
    "name": "SELASI"
  },
  {
    "code": 8109050003,
    "keccode": 8109050,
    "name": "ELARA"
  },
  {
    "code": 8109050004,
    "keccode": 8109050,
    "name": "LUMOY"
  },
  {
    "code": 8109050005,
    "keccode": 8109050,
    "name": "MASAWOY"
  },
  {
    "code": 8109050006,
    "keccode": 8109050,
    "name": "ULIMA"
  },
  {
    "code": 8109050007,
    "keccode": 8109050,
    "name": "KAMPUNG BARU"
  }
]