[
  {
    "code": 1808053001,
    "keccode": 1808053,
    "name": "BAKUNG UDIK"
  },
  {
    "code": 1808053002,
    "keccode": 1808053,
    "name": "BAKUNG ILIR"
  },
  {
    "code": 1808053003,
    "keccode": 1808053,
    "name": "GUNUNG TAPA"
  },
  {
    "code": 1808053004,
    "keccode": 1808053,
    "name": "GEDUNG MENENG"
  },
  {
    "code": 1808053008,
    "keccode": 1808053,
    "name": "GEDUNG BANDAR RAHAYU"
  },
  {
    "code": 1808053009,
    "keccode": 1808053,
    "name": "GUNUNG TAPA ILIR"
  },
  {
    "code": 1808053010,
    "keccode": 1808053,
    "name": "GUNUNG TAPA TENGAH"
  },
  {
    "code": 1808053011,
    "keccode": 1808053,
    "name": "GUNUNG TAPA UDIK"
  },
  {
    "code": 1808053012,
    "keccode": 1808053,
    "name": "GEDUNG BANDAR REJO"
  },
  {
    "code": 1808053013,
    "keccode": 1808053,
    "name": "BAKUNG RAHAYU"
  },
  {
    "code": 1808053014,
    "keccode": 1808053,
    "name": "GEDUNG MENENG BARU"
  }
]