[
  {
    "code": 3315030001,
    "keccode": 3315030,
    "name": "LAJER"
  },
  {
    "code": 3315030002,
    "keccode": 3315030,
    "name": "SEDADI"
  },
  {
    "code": 3315030003,
    "keccode": 3315030,
    "name": "BOLOGARANG"
  },
  {
    "code": 3315030004,
    "keccode": 3315030,
    "name": "KARANGWADER"
  },
  {
    "code": 3315030005,
    "keccode": 3315030,
    "name": "TOKO"
  },
  {
    "code": 3315030006,
    "keccode": 3315030,
    "name": "PENGKOL"
  },
  {
    "code": 3315030007,
    "keccode": 3315030,
    "name": "LEYANGAN"
  },
  {
    "code": 3315030008,
    "keccode": 3315030,
    "name": "WATU PAWON"
  },
  {
    "code": 3315030010,
    "keccode": 3315030,
    "name": "JIPANG"
  },
  {
    "code": 3315030011,
    "keccode": 3315030,
    "name": "KRAMAT"
  },
  {
    "code": 3315030013,
    "keccode": 3315030,
    "name": "WEDORO"
  },
  {
    "code": 3315030014,
    "keccode": 3315030,
    "name": "KLUWAN"
  },
  {
    "code": 3315030015,
    "keccode": 3315030,
    "name": "KARANGPAING"
  },
  {
    "code": 3315030016,
    "keccode": 3315030,
    "name": "PULUTAN"
  },
  {
    "code": 3315030017,
    "keccode": 3315030,
    "name": "WINONG"
  },
  {
    "code": 3315030018,
    "keccode": 3315030,
    "name": "WOLO"
  },
  {
    "code": 3315030020,
    "keccode": 3315030,
    "name": "PENAWANGAN"
  }
]