[
  {
    "code": 5313121001,
    "keccode": 5313121,
    "name": "LALONG"
  },
  {
    "code": 5313121002,
    "keccode": 5313121,
    "name": "BANGKA KENDA"
  },
  {
    "code": 5313121004,
    "keccode": 5313121,
    "name": "BANGKA JONG"
  },
  {
    "code": 5313121005,
    "keccode": 5313121,
    "name": "WAE RII"
  },
  {
    "code": 5313121006,
    "keccode": 5313121,
    "name": "LONGKO"
  },
  {
    "code": 5313121007,
    "keccode": 5313121,
    "name": "RANAKA"
  },
  {
    "code": 5313121008,
    "keccode": 5313121,
    "name": "GOLO MENDO"
  },
  {
    "code": 5313121009,
    "keccode": 5313121,
    "name": "GOLO CADOR"
  },
  {
    "code": 5313121010,
    "keccode": 5313121,
    "name": "COMPANG NDEHES"
  },
  {
    "code": 5313121011,
    "keccode": 5313121,
    "name": "POCO"
  },
  {
    "code": 5313121012,
    "keccode": 5313121,
    "name": "SATAR NGKELING"
  },
  {
    "code": 5313121013,
    "keccode": 5313121,
    "name": "GOLO WUA"
  },
  {
    "code": 5313121014,
    "keccode": 5313121,
    "name": "GOLO WATU"
  },
  {
    "code": 5313121015,
    "keccode": 5313121,
    "name": "RANGGI"
  },
  {
    "code": 5313121016,
    "keccode": 5313121,
    "name": "WAE MULU"
  },
  {
    "code": 5313121017,
    "keccode": 5313121,
    "name": "BENTENG POCO"
  }
]