[
  {
    "code": 3507160001,
    "keccode": 3507160,
    "name": "JENGGOLO"
  },
  {
    "code": 3507160003,
    "keccode": 3507160,
    "name": "KEMIRI"
  },
  {
    "code": 3507160004,
    "keccode": 3507160,
    "name": "TEGALSARI"
  },
  {
    "code": 3507160005,
    "keccode": 3507160,
    "name": "MANGUNREJO"
  },
  {
    "code": 3507160006,
    "keccode": 3507160,
    "name": "PANGGUNGREJO"
  },
  {
    "code": 3507160007,
    "keccode": 3507160,
    "name": "KEDUNGPEDARINGAN"
  },
  {
    "code": 3507160008,
    "keccode": 3507160,
    "name": "PENARUKAN"
  },
  {
    "code": 3507160009,
    "keccode": 3507160,
    "name": "CEPOKOMULYO"
  },
  {
    "code": 3507160010,
    "keccode": 3507160,
    "name": "KEPANJEN"
  },
  {
    "code": 3507160011,
    "keccode": 3507160,
    "name": "TALANGAGUNG"
  },
  {
    "code": 3507160012,
    "keccode": 3507160,
    "name": "DILEM"
  },
  {
    "code": 3507160013,
    "keccode": 3507160,
    "name": "ARDIREJO"
  },
  {
    "code": 3507160014,
    "keccode": 3507160,
    "name": "SUKORAHARJO"
  },
  {
    "code": 3507160015,
    "keccode": 3507160,
    "name": "CURUNG REJO"
  },
  {
    "code": 3507160016,
    "keccode": 3507160,
    "name": "JATIREJOYOSO"
  },
  {
    "code": 3507160017,
    "keccode": 3507160,
    "name": "NGADILANGKUNG"
  },
  {
    "code": 3507160018,
    "keccode": 3507160,
    "name": "MOJOSARI"
  }
]