[
  {
    "code": 3319060001,
    "keccode": 3319060,
    "name": "SADANG"
  },
  {
    "code": 3319060002,
    "keccode": 3319060,
    "name": "BULUNG CANGKRING"
  },
  {
    "code": 3319060003,
    "keccode": 3319060,
    "name": "BULUNG KULON"
  },
  {
    "code": 3319060004,
    "keccode": 3319060,
    "name": "SIDOMULYO"
  },
  {
    "code": 3319060005,
    "keccode": 3319060,
    "name": "GONDOHARUM"
  },
  {
    "code": 3319060006,
    "keccode": 3319060,
    "name": "TERBAN"
  },
  {
    "code": 3319060007,
    "keccode": 3319060,
    "name": "PLADEN"
  },
  {
    "code": 3319060008,
    "keccode": 3319060,
    "name": "KLALING"
  },
  {
    "code": 3319060009,
    "keccode": 3319060,
    "name": "JEKULO"
  },
  {
    "code": 3319060010,
    "keccode": 3319060,
    "name": "HADIPOLO"
  },
  {
    "code": 3319060011,
    "keccode": 3319060,
    "name": "TANJUNG REJO"
  },
  {
    "code": 3319060012,
    "keccode": 3319060,
    "name": "HONGGOSOCO"
  }
]