[
  {
    "code": 3312020001,
    "keccode": 3312020,
    "name": "PARANGGUPITO"
  },
  {
    "code": 3312020002,
    "keccode": 3312020,
    "name": "GUDANGHARJO"
  },
  {
    "code": 3312020003,
    "keccode": 3312020,
    "name": "GUNTURHARJO"
  },
  {
    "code": 3312020004,
    "keccode": 3312020,
    "name": "GENDAYAKAN"
  },
  {
    "code": 3312020005,
    "keccode": 3312020,
    "name": "SAMBIHARJO"
  },
  {
    "code": 3312020006,
    "keccode": 3312020,
    "name": "KETOS"
  },
  {
    "code": 3312020007,
    "keccode": 3312020,
    "name": "SONGBLEDEG"
  },
  {
    "code": 3312020008,
    "keccode": 3312020,
    "name": "JOHUNUT"
  }
]