[
  {
    "code": 7371050001,
    "keccode": 7371050,
    "name": "LAE - LAE"
  },
  {
    "code": 7371050002,
    "keccode": 7371050,
    "name": "LOSARI"
  },
  {
    "code": 7371050003,
    "keccode": 7371050,
    "name": "MANGKURA"
  },
  {
    "code": 7371050004,
    "keccode": 7371050,
    "name": "PISANG SELATAN"
  },
  {
    "code": 7371050005,
    "keccode": 7371050,
    "name": "LAJANGIRU"
  },
  {
    "code": 7371050006,
    "keccode": 7371050,
    "name": "SAWERIGADING"
  },
  {
    "code": 7371050007,
    "keccode": 7371050,
    "name": "MALOKU"
  },
  {
    "code": 7371050008,
    "keccode": 7371050,
    "name": "BULOGADING"
  },
  {
    "code": 7371050009,
    "keccode": 7371050,
    "name": "BARU"
  },
  {
    "code": 7371050010,
    "keccode": 7371050,
    "name": "PISANG UTARA"
  }
]