[
  {
    "code": 7407030001,
    "keccode": 7407030,
    "name": "HORUO"
  },
  {
    "code": 7407030002,
    "keccode": 7407030,
    "name": "SOMBANO"
  },
  {
    "code": 7407030003,
    "keccode": 7407030,
    "name": "LAU-LUA"
  },
  {
    "code": 7407030004,
    "keccode": 7407030,
    "name": "SAMABAHARI"
  },
  {
    "code": 7407030005,
    "keccode": 7407030,
    "name": "AMBEUA"
  },
  {
    "code": 7407030006,
    "keccode": 7407030,
    "name": "LAGIWAE"
  },
  {
    "code": 7407030007,
    "keccode": 7407030,
    "name": "OLLO"
  },
  {
    "code": 7407030008,
    "keccode": 7407030,
    "name": "BURANGA"
  },
  {
    "code": 7407030009,
    "keccode": 7407030,
    "name": "BALASUNA"
  },
  {
    "code": 7407030010,
    "keccode": 7407030,
    "name": "MANTIGOLA MAKMUR"
  },
  {
    "code": 7407030011,
    "keccode": 7407030,
    "name": "BALASUNA SELATAN"
  },
  {
    "code": 7407030012,
    "keccode": 7407030,
    "name": "OLLO SELATAN"
  },
  {
    "code": 7407030013,
    "keccode": 7407030,
    "name": "WADURI"
  },
  {
    "code": 7407030014,
    "keccode": 7407030,
    "name": "LEFUTO"
  },
  {
    "code": 7407030015,
    "keccode": 7407030,
    "name": "AMBEUA RAYA"
  },
  {
    "code": 7407030016,
    "keccode": 7407030,
    "name": "KALIMAS"
  }
]