[
  {
    "code": 3211181001,
    "keccode": 3211181,
    "name": "WANAJAYA"
  },
  {
    "code": 3211181002,
    "keccode": 3211181,
    "name": "WANASARI"
  },
  {
    "code": 3211181003,
    "keccode": 3211181,
    "name": "PAMEKARSARI"
  },
  {
    "code": 3211181004,
    "keccode": 3211181,
    "name": "SURIAN"
  },
  {
    "code": 3211181005,
    "keccode": 3211181,
    "name": "TANJUNG"
  },
  {
    "code": 3211181006,
    "keccode": 3211181,
    "name": "RANGGASARI"
  },
  {
    "code": 3211181007,
    "keccode": 3211181,
    "name": "SURIAMEDAL"
  },
  {
    "code": 3211181008,
    "keccode": 3211181,
    "name": "SURIAMUKTI"
  },
  {
    "code": 3211181009,
    "keccode": 3211181,
    "name": "NANJUNGWANGI"
  }
]