[
  {
    "code": 7371111001,
    "keccode": 7371111,
    "name": "TAMALANREA INDAH"
  },
  {
    "code": 7371111002,
    "keccode": 7371111,
    "name": "TAMALANREA JAYA"
  },
  {
    "code": 7371111003,
    "keccode": 7371111,
    "name": "TAMALANREA"
  },
  {
    "code": 7371111004,
    "keccode": 7371111,
    "name": "KAPASA"
  },
  {
    "code": 7371111005,
    "keccode": 7371111,
    "name": "PARANG LOE"
  },
  {
    "code": 7371111006,
    "keccode": 7371111,
    "name": "BIRA"
  },
  {
    "code": 7371111008,
    "keccode": 7371111,
    "name": "KAPASA RAYA"
  }
]