[
  {
    "code": 3302100001,
    "keccode": 3302100,
    "name": "SROWOT"
  },
  {
    "code": 3302100002,
    "keccode": 3302100,
    "name": "SURO"
  },
  {
    "code": 3302100003,
    "keccode": 3302100,
    "name": "KALIORI"
  },
  {
    "code": 3302100004,
    "keccode": 3302100,
    "name": "WLAHAR WETAN"
  },
  {
    "code": 3302100005,
    "keccode": 3302100,
    "name": "PEKAJA"
  },
  {
    "code": 3302100006,
    "keccode": 3302100,
    "name": "KARANGDADAP"
  },
  {
    "code": 3302100007,
    "keccode": 3302100,
    "name": "KALIBAGOR"
  },
  {
    "code": 3302100008,
    "keccode": 3302100,
    "name": "PAJERUKAN"
  },
  {
    "code": 3302100009,
    "keccode": 3302100,
    "name": "PETIR"
  },
  {
    "code": 3302100010,
    "keccode": 3302100,
    "name": "KALICUPAK KIDUL"
  },
  {
    "code": 3302100011,
    "keccode": 3302100,
    "name": "KALICUPAK LOR"
  },
  {
    "code": 3302100012,
    "keccode": 3302100,
    "name": "KALISOGRA WETAN"
  }
]