[
  {
    "code": 1608102001,
    "keccode": 1608102,
    "name": "CUKOH NAU"
  },
  {
    "code": 1608102002,
    "keccode": 1608102,
    "name": "PECAH PINGGAN"
  },
  {
    "code": 1608102003,
    "keccode": 1608102,
    "name": "UJAN MAS"
  },
  {
    "code": 1608102004,
    "keccode": 1608102,
    "name": "PULAU KEMUNING"
  },
  {
    "code": 1608102005,
    "keccode": 1608102,
    "name": "TANAH PILIH"
  },
  {
    "code": 1608102006,
    "keccode": 1608102,
    "name": "GUNTUNG JAYA"
  },
  {
    "code": 1608102007,
    "keccode": 1608102,
    "name": "SIMPANG LUAS"
  },
  {
    "code": 1608102008,
    "keccode": 1608102,
    "name": "SEBAJA"
  },
  {
    "code": 1608102009,
    "keccode": 1608102,
    "name": "SADAU JAYA"
  }
]