[
  {
    "code": 5310010001,
    "keccode": 5310010,
    "name": "WOLOWIRO"
  },
  {
    "code": 5310010002,
    "keccode": 5310010,
    "name": "MAULOO"
  },
  {
    "code": 5310010004,
    "keccode": 5310010,
    "name": "PAGA"
  },
  {
    "code": 5310010008,
    "keccode": 5310010,
    "name": "LENANDARETA"
  },
  {
    "code": 5310010015,
    "keccode": 5310010,
    "name": "MASEBEWA"
  },
  {
    "code": 5310010016,
    "keccode": 5310010,
    "name": "WOLOREGA"
  },
  {
    "code": 5310010017,
    "keccode": 5310010,
    "name": "WOLOWONA"
  }
]